dlpacker/__init__.py
dlpacker/data/DLPacker_weights.7z.001
dlpacker/data/DLPacker_weights.7z.002
dlpacker/data/DLPacker_weights.7z.003
dlpacker/data/DLPacker_weights.7z.004
dlpacker/data/DLPacker_weights.7z.005
dlpacker/data/DLPacker_weights.7z.006
dlpacker/data/DLPacker_weights.7z.007
dlpacker/data/DLPacker_weights.7z.008
dlpacker/data/DLPacker_weights.7z.009
dlpacker/data/DLPacker_weights.7z.010
dlpacker/data/DLPacker_weights.7z.011
dlpacker/data/DLPacker_weights.7z.012
dlpacker/data/charges.rtp
dlpacker/data/library.npz
dlpacker/data/reference.pdb
dlpacker/dlpacker.py
dlpacker/utils.py
dlpacker-1.0.3.dist-info/LICENSE
dlpacker-1.0.3.dist-info/METADATA
dlpacker-1.0.3.dist-info/WHEEL
dlpacker-1.0.3.dist-info/RECORD
