Metadata-Version: 2.1
Name: dlpacker
Version: 1.0.3
Summary: DLPacker: Deep Learning-based prediction of amino acid side chain conformations in proteins
Home-page: https://github.com/nekitmm/DLPacker
License: MIT
Author: Mikita Misiura
Author-email: mikita.misiura@gmail.com
Requires-Python: >=3.8
Classifier: License :: OSI Approved :: MIT License
Classifier: Programming Language :: Python :: 3
Classifier: Programming Language :: Python :: 3.8
Classifier: Programming Language :: Python :: 3.9
Classifier: Programming Language :: Python :: 3.10
Classifier: Programming Language :: Python :: 3.11
Classifier: Programming Language :: Python :: 3.12
Classifier: Topic :: Scientific/Engineering :: Bio-Informatics
Requires-Dist: biopython (>=1.78)
Requires-Dist: numpy (>=1.19.2,<2.0.0)
Requires-Dist: py7zr (==0.20.8)
Requires-Dist: tensorflow (>=2.5.0,<2.16.0)
Project-URL: Repository, https://github.com/nekitmm/DLPacker
